<DataList>
  <Info code="Rope" language="KR">
    <Audio code="JP_001" name="획득" info="안녕, 로프라고 불러줘. 아, 이거 네 ID 카드지? 응? 왜 내가 가지고 있냐고? 그건 비.밀이야." />
    <Audio code="JP_002" name="어시스턴트 임명" info="박사, 잊어버린 거, 없지?" />
    <Audio code="JP_003" name="인사" info="네에, 박사." />

    <Audio code="JP_004" name="대화 1" info="다른 사람들 주머니에서 훔친걸 가지고 먹고 살아간다고? 어쩔 수가 없잖아, 이렇게 살아왔으니까. 이렇게라도 안했으면 이미 굶어 죽었을거라고." />
    <Audio code="JP_005" name="대화 2" info="튼튼하고 오래쓸 수 있는 갈고리는 결국 줄이 중요하단 말야. 응? 왜 그렇게 갈고리를 좋아하냐고? 맨손으로 빌딩을 한 번 올라보면 알게 될 거야." />
    <Audio code="JP_006" name="대화 3" info="알겠어, 박사가 말하는건 잘 들을테니까. 이제 기숙사로 돌아가도 좋아? 좀 있다 할 게 있으니까. 어, 또 있다고? 이제 그만 좀 해줘, 부탁이니까!" />
    <Audio code="JP_007" name="1차 정예화 후 대사" info="박사네가 없었다면, 아직 바깥 세상의 공기를 마시지도 못했을지도 몰라. 그보다 어떻게 날 알고 있었어? 응? 내 실력을 풍문으로 들어서? 그렇구나." />
    <Audio code="JP_008" name="2차 정예화 후 대사" info="슬럼에서 살아남는 수단은 여럿 있어. 다만 그걸 못하고 죽어가는 녀석들이 더 많아. 나에겐 달리 살길이 없었어. 박사도 그걸 이해해줬으면 좋겠어." />
    <Audio code="JP_009" name="신뢰도 상승 후 대사 1" info="부모에게 집에서 쫓겨나서, 혼자서 거리를 헤메이면서 필사적으로 살아남는 것보다, 로도스에서 사는 게 당연히 훨씬 더 편하잖아?" />
    <Audio code="JP_010" name="신뢰도 상승 후 대사 2" info="이 병에 걸려서 죽어가는 녀석들을 잔뜩 봤으니까, 나도 그렇게 되겠지 하고 포기했을때 로도스가 날 받아줬어. 솔직히 말해줬으면 해, 박사. …내 병은 고칠 수 있는 거지? 안될 수도 있다고? … 뭐, 그건 그것대로 괜찮으려나." />
    <Audio code="JP_011" name="신뢰도 상승 후 대사 3" info="옛날에는 내일 먹을 게 있을지 없을지도 몰랐는데, 지금은 언제나 배불리 먹을 수 있어. 로도스의 이런 점은 칭찬할 수밖에 없겠네. 흥, 내게 고맙다는 소리를 듣고 싶다고? 포기하는 게 좋을걸? … 아, 이미 말해버렸잖아." />

    <Audio code="JP_012" name="시설에 배치" info="이 방에 통풍구는 있어? 아니, 그냥 물어봤어." />
    <Audio code="JP_013" name="터치" info="으아악! 날 붙잡으러 온 거야?" />
    <Audio code="JP_014" name="신뢰도 터치" info="나도 평범한 여자아이가 되는 방법을 알아보고 싶지만, 그렇지만 있잖아. 나한텐 별로 안 어울리지 않을까?" />
    <Audio code="JP_015" name="방치" info="이 의자… 젠장, 너무 기분이 좋잖아!" />
    <Audio code="JP_016" name="작전 기록 학습" info="이런 걸 봐서 정말로 도움이 되는 거야?" />
    <Audio code="JP_017" name="1차 정예화 시" info="그것보다 급여, 급여나 올려줘! 승진 따위보다 급여를 올리는 쪽이 더 고맙다고!" />
    <Audio code="JP_018" name="2차 정예화 시" info="좋아, 급여도 잔뜩 받았으니까, 제대로 일해볼까?"/>
    <Audio code="JP_019" name="팀 배치" info="응, 응, 여기 왔어." />
    <Audio code="JP_020" name="팀장 임명" info="대장을 하라고? 평소라면 보너스를 받아야겠지만, 박사를 봐서 통상요금으로 해줄게." />

    <Audio code="JP_021" name="작전 출발" info="지형이나 루트는 사전에 파악해둬서 손해볼 거 없어. 선배로서 해주는 조언이야." />
    <Audio code="JP_022" name="작전 개시" info="자, 그럼 오늘 적들은 뭔가 좋은 거라도 가지고 있으려나~" />
    <Audio code="JP_023" name="오퍼레이터 선택 1" info="정면승부는 내 스타일이 아니란 말이지." />
    <Audio code="JP_024" name="오퍼레이터 선택 2" info="내 특기, 제대로 살려줘. 부.탁.이.야" />
    <Audio code="JP_025" name="배치 1" info="살금 살금…" />
    <Audio code="JP_026" name="배치 2" info="장소는 여기로 하면 되려나." />
    <Audio code="JP_027" name="작전 중 1" info="하하!" />
    <Audio code="JP_028" name="작전 중 2" info="좋아, 더 오라고!" />
    <Audio code="JP_029" name="작전 중 3" info="흐압!" />
    <Audio code="JP_030" name="작전 중 4" info="이 갈고리에 한 번 잡히면, 도망치지 못한다고!" />
    <Audio code="JP_031" name="작전 종료 - 하드모드" info="평소보다 더 자극적인 전투였어! 물론 보상도 말야!" />
    <Audio code="JP_032" name="작전 종료 - 3★" info="좋은 건 적이 가지고 있게 내버려두기 아까워, 그렇게 생각하지 않아?" />
    <Audio code="JP_033" name="작전 종료 - 1★,2★" info="몇 명 정도가 도망쳤다고? 그 정도라면 내버려두자. 마음을 고쳐먹을지도 모르잖아?" />
    <Audio code="JP_034" name="작전 실패" info="야, 야! 나랑 같이 도망치자! 목숨은 중요하다고!" />
  </Info>
</DataList>